mbds/__init__.py
mbds/embed.py
mbds/space.py
mbds/types.py
mbds-0.0.1.dist-info/METADATA
mbds-0.0.1.dist-info/WHEEL
mbds-0.0.1.dist-info/top_level.txt
mbds-0.0.1.dist-info/RECORD
