Metadata-Version: 2.1
Name: mbds
Version: 0.0.1
Summary: Unix embedding driver for software 2.0
Author-email: Jason Wilkes <notarealdeveloper@gmail.com>
Project-URL: source, https://github.com/notarealdeveloper/mbds
Project-URL: download, https://pypi.org/project/mbds/#files
